index.py
podcastsdata-0.0.1.dist-info/LICENSE
podcastsdata-0.0.1.dist-info/METADATA
podcastsdata-0.0.1.dist-info/WHEEL
podcastsdata-0.0.1.dist-info/top_level.txt
podcastsdata-0.0.1.dist-info/RECORD
