Metadata-Version: 2.1
Name: podcastsdata
Version: 0.0.1
Summary: Package that can get analytics from anchor
Author-email: Oliver Vuorenmaa <vuoreol@gmail.com>
License: GNU AFFERO GENERAL PUBLIC LICENSE
Project-URL: Homepage, https://github.com/forpodcasters/podcast_analytics
Project-URL: Bug Tracker, https://github.com/forpodcasters/podcast_analytics/issues
Classifier: Programming Language :: Python :: 3
Classifier: License :: OSI Approved :: MIT License
Classifier: Operating System :: OS Independent
Requires-Python: >=3.7
License-File: LICENSE
